src/FSM.v
// Copyright (C) 2025  Altera Corporation. All rights reserved.
// Your use of Altera Corporation's design tools, logic functions 
// and other software and tools, and any partner logic 
// functions, and any output files from any of the foregoing 
// (including device programming or simulation files), and any 
// associated documentation or information are expressly subject 
// to the terms and conditions of the Altera Program License 
// Subscription Agreement, the Altera Quartus Prime License Agreement,
// the Altera IP License Agreement, or other applicable license
// agreement, including, without limitation, that your use is for
// the sole purpose of programming logic devices manufactured by
// Altera and sold by Altera or its authorized distributors.  Please
// refer to the Altera Software License Subscription Agreements 
// on the Quartus Prime software download page.

// PROGRAM		"Quartus Prime"
// VERSION		"Version 25.1std.0 Build 1129 10/21/2025 SC Lite Edition"
// CREATED		"Mon Mar 30 20:07:54 2026"

module FSM(
	F,
	S_t,
	J1,
	J2,
	clock,
	rst_n,
	L,
	E,
	B,
	I1,
	I2,
	out_Q1,
	out_Q2,
	out_Q0
);


input wire	F;
input wire	S_t;
input wire	J1;
input wire	J2;
input wire	clock;
input wire	rst_n;
output wire	L;
output wire	E;
output wire	B;
output wire	I1;
output wire	I2;
output wire	out_Q1;
output wire	out_Q2;
output wire	out_Q0;

wire	D1_out;
wire	D2_out;
wire	not_Q2;
reg	Q0;
reg	Q1;
reg	Q2;
wire	SYNTHESIZED_WIRE_0;
wire	SYNTHESIZED_WIRE_26;
wire	SYNTHESIZED_WIRE_3;
wire	SYNTHESIZED_WIRE_4;
wire	SYNTHESIZED_WIRE_5;
wire	SYNTHESIZED_WIRE_6;
wire	SYNTHESIZED_WIRE_7;
wire	SYNTHESIZED_WIRE_8;
wire	SYNTHESIZED_WIRE_27;
wire	SYNTHESIZED_WIRE_10;
wire	SYNTHESIZED_WIRE_12;
wire	SYNTHESIZED_WIRE_14;
wire	SYNTHESIZED_WIRE_15;
wire	SYNTHESIZED_WIRE_16;
wire	SYNTHESIZED_WIRE_17;
wire	SYNTHESIZED_WIRE_18;
wire	SYNTHESIZED_WIRE_19;
wire	SYNTHESIZED_WIRE_28;
wire	SYNTHESIZED_WIRE_22;
wire	SYNTHESIZED_WIRE_23;
wire	SYNTHESIZED_WIRE_24;
wire	SYNTHESIZED_WIRE_25;

assign	SYNTHESIZED_WIRE_26 = 1;




always@(posedge clock or negedge rst_n or negedge SYNTHESIZED_WIRE_26)
begin
if (!rst_n)
	begin
	Q0 <= 0;
	end
else
if (!SYNTHESIZED_WIRE_26)
	begin
	Q0 <= 1;
	end
else
	begin
	Q0 <= SYNTHESIZED_WIRE_0;
	end
end


always@(posedge clock or negedge rst_n or negedge SYNTHESIZED_WIRE_26)
begin
if (!rst_n)
	begin
	Q1 <= 0;
	end
else
if (!SYNTHESIZED_WIRE_26)
	begin
	Q1 <= 1;
	end
else
	begin
	Q1 <= D1_out;
	end
end

assign	SYNTHESIZED_WIRE_8 = J2;

assign	SYNTHESIZED_WIRE_7 = SYNTHESIZED_WIRE_3 | SYNTHESIZED_WIRE_4 | SYNTHESIZED_WIRE_5;

assign	SYNTHESIZED_WIRE_6 = J1 ~^ J2;

assign	SYNTHESIZED_WIRE_4 = Q1 & Q0 & SYNTHESIZED_WIRE_6;

assign	not_Q2 =  ~Q2;

assign	D1_out = not_Q2 & SYNTHESIZED_WIRE_7;

assign	SYNTHESIZED_WIRE_16 = SYNTHESIZED_WIRE_8 & Q0 & Q1;

assign	SYNTHESIZED_WIRE_15 = Q1 & SYNTHESIZED_WIRE_27 & F;

assign	SYNTHESIZED_WIRE_14 = SYNTHESIZED_WIRE_10 & SYNTHESIZED_WIRE_27 & S_t;

assign	SYNTHESIZED_WIRE_0 = not_Q2 & SYNTHESIZED_WIRE_12;


always@(posedge clock or negedge rst_n or negedge SYNTHESIZED_WIRE_26)
begin
if (!rst_n)
	begin
	Q2 <= 0;
	end
else
if (!SYNTHESIZED_WIRE_26)
	begin
	Q2 <= 1;
	end
else
	begin
	Q2 <= D2_out;
	end
end


assign	SYNTHESIZED_WIRE_27 =  ~Q0;

assign	SYNTHESIZED_WIRE_10 =  ~Q1;

assign	SYNTHESIZED_WIRE_12 = SYNTHESIZED_WIRE_14 | SYNTHESIZED_WIRE_15 | SYNTHESIZED_WIRE_16;

assign	L = Q2 & SYNTHESIZED_WIRE_17 & Q0;

assign	E = Q2 & Q1 & SYNTHESIZED_WIRE_18;

assign	B = Q2 & Q1 & Q0;

assign	I1 = SYNTHESIZED_WIRE_19 & SYNTHESIZED_WIRE_28 & Q2;

assign	I2 = Q0 & SYNTHESIZED_WIRE_28 & Q2;

//assign	Q2 =  ~Q2;

assign	SYNTHESIZED_WIRE_23 =  ~Q0;

assign	SYNTHESIZED_WIRE_17 =  ~Q1;

assign	SYNTHESIZED_WIRE_18 =  ~Q0;

assign	SYNTHESIZED_WIRE_28 =  ~Q1;

assign	SYNTHESIZED_WIRE_19 =  ~Q0;


assign	D2_out = SYNTHESIZED_WIRE_22 & SYNTHESIZED_WIRE_23 & Q1 & Q2;

assign	SYNTHESIZED_WIRE_22 = J1 ^ J2;

assign	SYNTHESIZED_WIRE_24 =  ~Q0;

assign	SYNTHESIZED_WIRE_25 =  ~Q1;

assign	SYNTHESIZED_WIRE_3 = Q1 & SYNTHESIZED_WIRE_24;

assign	SYNTHESIZED_WIRE_5 = SYNTHESIZED_WIRE_25 & Q0;

assign	out_Q1 = Q1;
assign	out_Q2 = Q2;
assign	out_Q0 = Q0;

endmodule

src/tb.v
`timescale 1ns/1ps

module tb_jogo();
    // Entradas (tipo reg para podermos manipular)
    reg clock;
    reg rst_n;
    reg S_t, F, J1, J2;

    // Saídas (tipo wire para lermos o resultado)
    wire L, E, B, I1, I2;
    wire out_Q2, out_Q1, out_Q0;

    // Instancia o seu circuito gerado pelo Quartus
    // Substitua "jogo_de_velocidade" pelo nome exato que estiver no seu .v principal
    FSM uut (
        .clock(clock),
        .rst_n(rst_n),
        .S_t(S_t),
        .F(F),
        .J1(J1),
        .J2(J2),
        .L(L),
        .E(E),
        .B(B),
        .I1(I1),
        .I2(I2),
        .out_Q0(out_Q0),
        .out_Q1(out_Q1),
        .out_Q2(out_Q2)
    );

    // Gerador de Clock contínuo (inverte a cada 10ns)
    always #10 clock = ~clock;

    // A "Linha do Tempo" da simulação
    initial begin
        // Cria o arquivo de formas de onda para o GTKWave
        $dumpfile("ondas.vcd");
        $dumpvars(0, tb_jogo);

        // 1. INÍCIO (Tudo em zero, máquina cravada no Reset)
        clock = 0;
        rst_n = 0; // RESET ATIVADO (0)
        S_t = 0; F = 0; J1 = 0; J2 = 0;

        // 2. LIBERA A MÁQUINA (Espera 40ns e sobe o reset para 1)
        #40;
        rst_n = 1; 

        // 3. APERTA O START (Espera 20ns, sobe o S_t, espera um clock e desce)
        #20;
        S_t = 1;
        #20;
        S_t = 0;

        // 4. FIM DO TEMPO (Espera a máquina contar tempo, e ativa o F)
        #60;
        F = 1;
        #20;
        F = 0;

        // 5. PONTO DO J1 (J1 é mais rápido e aperta o botão)
        #40;
        J1 = 1;
        #20;
        J1 = 0;

        // Fim da simulação após 100ns
        #100;
        $finish;
    end
endmodule

src/ondas.vcd
$date
	Mon Mar 30 20:13:22 2026
$end
$version
	Icarus Verilog
$end
$timescale
	1ps
$end
$scope module tb_jogo $end
$var wire 1 ! out_Q2 $end
$var wire 1 " out_Q1 $end
$var wire 1 # out_Q0 $end
$var wire 1 $ L $end
$var wire 1 % I2 $end
$var wire 1 & I1 $end
$var wire 1 ' E $end
$var wire 1 ( B $end
$var reg 1 ) F $end
$var reg 1 * J1 $end
$var reg 1 + J2 $end
$var reg 1 , S_t $end
$var reg 1 - clock $end
$var reg 1 . rst_n $end
$scope module uut $end
$var wire 1 ( B $end
$var wire 1 / D1_out $end
$var wire 1 0 D2_out $end
$var wire 1 ' E $end
$var wire 1 ) F $end
$var wire 1 & I1 $end
$var wire 1 % I2 $end
$var wire 1 * J1 $end
$var wire 1 + J2 $end
$var wire 1 $ L $end
$var wire 1 1 SYNTHESIZED_WIRE_0 $end
$var wire 1 2 SYNTHESIZED_WIRE_10 $end
$var wire 1 3 SYNTHESIZED_WIRE_12 $end
$var wire 1 4 SYNTHESIZED_WIRE_14 $end
$var wire 1 5 SYNTHESIZED_WIRE_15 $end
$var wire 1 6 SYNTHESIZED_WIRE_16 $end
$var wire 1 7 SYNTHESIZED_WIRE_17 $end
$var wire 1 8 SYNTHESIZED_WIRE_18 $end
$var wire 1 9 SYNTHESIZED_WIRE_19 $end
$var wire 1 : SYNTHESIZED_WIRE_22 $end
$var wire 1 ; SYNTHESIZED_WIRE_23 $end
$var wire 1 < SYNTHESIZED_WIRE_24 $end
$var wire 1 = SYNTHESIZED_WIRE_25 $end
$var wire 1 > SYNTHESIZED_WIRE_26 $end
$var wire 1 ? SYNTHESIZED_WIRE_27 $end
$var wire 1 @ SYNTHESIZED_WIRE_28 $end
$var wire 1 A SYNTHESIZED_WIRE_3 $end
$var wire 1 B SYNTHESIZED_WIRE_4 $end
$var wire 1 C SYNTHESIZED_WIRE_5 $end
$var wire 1 D SYNTHESIZED_WIRE_6 $end
$var wire 1 E SYNTHESIZED_WIRE_7 $end
$var wire 1 F SYNTHESIZED_WIRE_8 $end
$var wire 1 , S_t $end
$var wire 1 - clock $end
$var wire 1 G not_Q2 $end
$var wire 1 # out_Q0 $end
$var wire 1 " out_Q1 $end
$var wire 1 ! out_Q2 $end
$var wire 1 . rst_n $end
$var reg 1 H Q0 $end
$var reg 1 I Q1 $end
$var reg 1 J Q2 $end
$upscope $end
$upscope $end
$enddefinitions $end
$comment Show the parameter values. $end
$dumpall
$end
#0
$dumpvars
0J
0I
0H
1G
0F
0E
1D
0C
0B
0A
1@
1?
1>
1=
1<
1;
0:
19
18
17
06
05
04
03
12
01
00
0/
0.
0-
0,
0+
0*
0)
0(
0'
0&
0%
0$
0#
0"
0!
$end
#10000
1-
#20000
0-
#30000
1-
#40000
0-
1.
#50000
1-
#60000
11
13
14
0-
1,
#70000
01
03
1/
04
1E
1C
0<
09
08
0;
0?
1#
1H
1-
#80000
0-
0,
#90000
1/
1E
1A
0=
0@
07
02
0C
1<
19
18
1;
1?
1"
1I
0#
0H
1-
#100000
0-
#110000
1-
#120000
0-
#130000
1-
#140000
11
13
15
0-
1)
#150000
01
03
05
0A
1B
0<
09
08
0;
0?
1#
1H
1-
#160000
0-
0)
#170000
1A
0B
1<
19
18
1;
1?
0#
0H
1-
#180000
0-
#190000
1-
#200000
0D
1:
0-
1*
#210000
1-
#220000
1D
0:
0-
0*
